friendly_idle/__init__.py
friendly_idle/__main__.py
friendly_idle/patch_idle.py
friendly_idle/patching_hook.py
friendly_idle-0.4.dist-info/LICENSE
friendly_idle-0.4.dist-info/METADATA
friendly_idle-0.4.dist-info/WHEEL
friendly_idle-0.4.dist-info/entry_points.txt
friendly_idle-0.4.dist-info/top_level.txt
friendly_idle-0.4.dist-info/RECORD
