Metadata-Version: 2.1
Name: friendly-idle
Version: 0.4
Summary: Customized version of IDLE for friendly/friendly-traceback.
Home-page: https://github.com/friendly-traceback/friendly_idle
Author: Andre Roberge
Author-email: Andre.Roberge@gmail.com
Classifier: Development Status :: 4 - Beta
Classifier: Environment :: Console
Classifier: License :: OSI Approved :: MIT License
Classifier: Programming Language :: Python :: 3
Classifier: Programming Language :: Python :: 3.8
Classifier: Programming Language :: Python :: 3.9
Classifier: Programming Language :: Python :: 3.10
Classifier: Programming Language :: Python :: 3.11
Classifier: Intended Audience :: Education
Classifier: Topic :: Education
Classifier: Topic :: Software Development :: Interpreters
Requires-Python: >=3.8.10
License-File: LICENSE
Requires-Dist: friendly (>=0.7.19)
Requires-Dist: friendly-traceback (>=0.7.47)
